{
	"name": "ds_src_file",
	"properties": {
		"linkedServiceName": {
			"referenceName": "ls_src1",
			"type": "LinkedServiceReference"
		},
		"folder": {
			"name": "Azure Data Factory Full Course (From Beginner to PRO) | ADF Real-Time Scenarios"
		},
		"annotations": [],
		"type": "DelimitedText",
		"typeProperties": {
			"location": {
				"type": "AzureBlobStorageLocation",
				"folderPath": "csvfiles",
				"container": "source"
			},
			"columnDelimiter": ",",
			"escapeChar": "\\",
			"firstRowAsHeader": true,
			"quoteChar": "\""
		},
		"schema": []
	}
}